Workbook

Sheet 01 Portal Master
A1: 01 Portal Master
A3: Priority Tier | B3: Company / Portal | C3: Type | D3: Main Website | E3: Tender Search Link | F3: Vendor/Award Link | G3: Login / DSC / Requirement | H3: Regulator Relevance | I3: Evidence / Current Note | J3: Next Action
A4: Tier 1 | B4: GAIL India | C4: PSU / Gas transmission + CGD parent | D4: https://gailtenders.in | E4: https://gailtenders.in/Gailtenders | F4: https://gailtenders.in/Gailtenders/writereaddata/AOC/ | G4: May need vendor login/DSC for bids | H4: High | I4: FOA/LOA/AOC PDFs openly available | J4: Use GAIL AOC and archive searches
A5: Tier 1 | B5: GAIL Gas | C5: CGD operator | D5: https://gailgas.com | E5: https://gailgas.com/stakeholder-zone/vendor-zone | F5: https://gailgas.com/stakeholder-zone/vendor-zone | G5: Likely GeM/portal depending tender | H5: High | I5: Vendor zone points to tender information system | J5: Search domestic/service regulators and GeM refs
A6: Tier 1 | B6: Indraprastha Gas (IGL) | C6: CGD operator | D6: https://www.iglonline.net | E6: https://tenders.iglonline.net/tenderList | F6: https://tenders.iglonline.net/tenderList | G6: Vendor registration listed on tender portal | H6: High | I6: Portal has active tenders, vendor portal, e-tender guide | J6: Search FRS/MRS/C&I regulators
A7: Tier 1 | B7: Mahanagar Gas (MGL) | C7: CGD operator | D7: https://www.mahanagargas.com | E7: https://www.mahanagargas.com/Tender | F7: https://www.mahanagargas.com/Tender | G7: SAP/RFx, DSC usually needed | H7: High | I7: Supplier bid guide shows digital signature requirement | J7: Need find archive/results
A8: Tier 1 | B8: Gujarat Gas (GGL) | C8: CGD operator | D8: https://www.gujaratgas.com | E8: https://www.gujaratgas.com/tenders/ | F8: https://www.gujaratgas.com/tenders/ | G8: nProcure registration; DSC likely | H8: High | I8: GGL tenders are published through nProcure | J8: Use nProcure support links
A9: Tier 1 | B9: Adani Total Gas (ATGL) | C9: CGD operator | D9: https://www.adanigas.com | E9: https://www.adanigas.com/commercials | F9: https://www.adanigas.com/commercials | G9: Vendor registration available | H9: High | I9: Commercials page has Vendor Registration, Tender and EOI | J9: Search tender category list
A10: Tier 1 | B10: Torrent Gas | C10: CGD operator | D10: https://www.torrentgas.com | E10: https://www.torrentgas.com/User/Info/Vendor | F10: https://www.torrentgas.com/User/Info/Vendor | G10: Vendor evaluation/registration | H10: High | I10: Vendor page lists procurement email | J10: procurement@torrentgas.com
A11: Tier 1 | B11: IndianOil-Adani Gas (IOAGPL) | C11: CGD JV | D11: https://ioagpl.com | E11: https://ioagpl.com/vendor-registration-form/ | F11: https://ioagpl.com/tenders/ | G11: Vendor form via courier/docs | H11: High | I11: Vendor registration form page lists required docs | J11: Search IOAGPL regulator on CPPP too
A12: Tier 1 | B12: Indian Oil Corporation (IOCL CGD) | C12: PSU CGD operator | D12: https://iocl.com | E12: https://iocl.com/tenders | F12: https://iocl.com/pages/cgd | G12: CPPP/IOCL portal/GeM | H12: High | I12: IOCL says it is present in 49 GAs with JVs | J12: Search organisation Indian Oil Corporation
A13: Tier 1 | B13: Bharat Petroleum (BPCL CGD) | C13: PSU CGD operator | D13: https://bharatpetroleum.in | E13: https://bharatpetroleum.in/tenders | F13: https://bharatpetroleum.in/bharat-petroleum-for/our-businesses/gas/city-gas-distribution | G13: CPPP/BPCL portal/GeM | H13: High | I13: BPCL CGD page confirms CGD business | J13: Search BPCL CGD regulator
A14: Tier 1 | B14: Hindustan Petroleum (HPCL CGD) | C14: PSU CGD operator | D14: https://www.hindustanpetroleum.com | E14: https://www.hindustanpetroleum.com/pages/tenders-and-contracts | F14: https://www.hindustanpetroleum.com | G14: CPPP/HPCL portal/GeM | H14: Medium | I14: Often central PSU procurement | J14: Search HPCL city gas distribution regulator
... A54: Tier 3 | B54: SAP Ariba Discovery | C54: Enterprise procurement | D54: https://www.ariba.com | E54: https://service.ariba.com | F54: https://discovery.ariba.com | G54: Registration | H54: Medium | I54: Many private/large utilities use Ariba-like RFx | J54: Track when cited in documents

Sheet 02 Search Keywords
A1: 02 Search Keywords
A3: Segment | B3: Keyword | C3: Meaning / Use | D3: Notes
A4: Domestic regulator | B4: domestic regulator | C4: Domestic PNG, 100 mbar to 21 mbar | D4: Use on all portals
A5: Service regulator | B5: service regulator | C5: 10/25/50/100 SCMH customer regulator | D5: High value vs domestic
A6: Commercial regulator | B6: commercial regulator | C6: C&I customer regulators | D6: Search C&I too
A7: Industrial regulator | B7: industrial regulator | C7: Industrial customer skid/regulator | D7: High margin
A8: Meter regulator | B8: meter regulator | C8: Regulator with meter / meter regulator | D8: Often bundled
A9: Pressure regulator | B9: pressure regulator | C9: Generic keyword | D9: Broad search
A10: Gas pressure regulator | B10: gas pressure regulator | C10: Specific keyword | D10: Good for CPPP
A11: Regulator skid | B11: regulator skid | C11: Skid/package system | D11: High value
A12: Metering skid | B12: metering skid | C12: Metering skid / RPD / turbine | D12: Comparable equipment
A13: MRS | B13: MRS | C13: Metering & regulating station | D13: Search acronym and full form
A14: DRS | B14: DRS | C14: District regulating station | D14: Search acronym and full form
... A27: CNG regulator | B27: CNG regulator | C27: CNG station/vehicle side often irrelevant | D27: Filter carefully

Sheet 03 How To Search
A1: 03 How To Search
A3: Portal | B3: Step 1 | C3: Step 2 | D3: Step 3 | E3: What to Save
A4: CPPP / etenders.gov.in | B4: Use Tenders in Archive first | C4: Organisation = GAIL / GAIL Gas / MNGL / IOCL / BPCL / HPCL / EIL / MECON | D4: Search each keyword separately | E4: Download NIT, Technical Volume, Price BOQ if open, AOC/LOA
A5: GAIL Tenders | B5: Use tender/AOC pages | C5: Search file names and award folders | D5: Try LOA/FOA/AOC PDF links | E5: Record tender no, LOA no, awarded vendor, item quantities
A6: GAIL Gas | B6: Vendor Zone / GeM references | C6: Search portal and Google with site:gailgas.com regulator | D6: Download GeM specification PDFs | E6: Record GeM bid no if present
A7: IGL | B7: Tender list and archive | C7: Search FRS/MRS/regulator/C&I | D7: Vendor registration may be needed | E7: Download active and corrigendum docs
A8: Gujarat Gas | B8: GGL tenders page points to nProcure | C8: Use nProcure open tenders/archive | D8: Registration/DSC likely | E8: Record nProcure tender ID
A9: Torrent Gas | B9: Vendor page and procurement email | C9: Search tender/category list | D9: Email procurement if docs hidden | E9: Record response status
A10: Adani Total Gas | B10: Commercials page | C10: Open Vendor Registration / Tender / EOI | D10: Category list can reveal procurement category | E10: Monitor steel pipeline and O&M projects
A11: MNGL | B11: Active tenders + CPPP | C11: Search regulator archive on CPPP | D11: DSC required for participation | E11: Good price benchmark source
A12: Gasonet | B12: Official tenders page | C12: PDF docs often public | D12: Use quantities from BOQ/SOR | E12: Good service/domestic regulator benchmark
A13: GeM | B13: Search by buyer / bid no | C13: Look for domestic/service regulator specs | D13: Prices often closed, specs useful | E13: Record GeM bid link and product specs

Sheet 04 Tender Register
A1: 04 Tender Register
A3: Tender ID | B3: Company | C3: Portal | D3: Tender Ref | E3: Tender Date | F3: Status | G3: Product Segment | H3: Product Description | I3: Qty | J3: UOM | K3: Winner | L3: Brand | M3: Total INR Basic | N3: GST INR | O3: Total INR Incl GST | P3: FX INR/EUR | Q3: Total EUR | R3: Unit EUR Basic | S3: Unit EUR Incl GST | T3: Source URL | U3: PDF Saved? | V3: Notes
A4: T-0001 | B4: GAIL India | C4: GAIL Tenders | D4: LOA 20250806_102439 | E4: 2025-06-11 | F4: Awarded | G4: Metering skid | H4: RPD metering skid / KG Basin | I4: 3 | J4: set/stream | K4: Kimpex Flow Pvt. Ltd. | L4: Unknown | M4: 3000222 | N4: 540039.96 | O4: 3540262 | P4: 106.75 | Q4: =O4/P4 | R4: =M4/I4/P4 | S4: =O4/I4/P4 | T4: https://gailtenders.in/Gailtenders/writereaddata/AOC/loa_20250806_102439.pdf | U4: Yes | V4: Existing tracker source
A5: T-0002 | B5: GAIL India | C5: GAIL Tenders | D5: FOA 20231230_102206 | E5: 2023-12-30 | F5: Awarded | G5: Gas meters | H5: Commercial/Domestic gas meters | J5: nos | K5: Kimpex / Raychem | L5: Unknown | P5: 106.75 | Q5: =IFERROR(O5/P5,"") | R5: =IFERROR(M5/I5/P5,"") | S5: =IFERROR(O5/I5/P5,"") | T5: https://gailtenders.in/Gailtenders/writereaddata/AOC/foa_20231230_102206.pdf | U5: Yes | V5: Meter benchmark, not regulator
A6: T-0003 | B6: Gasonet | C6: Gasonet Tenders | D6: GASONET/C&P-GSL/REGULATOR-/2023-24/014 | E6: 2024-03-10 | F6: Docs Found | G6: Domestic + Service Regulator | H6: Domestic regulators and service regulators | I6: 938 | J6: mixed | K6: Not found | L6: Unknown | P6: 106.75 | Q6: =IFERROR(O6/P6,"") | R6: =IFERROR(M6/I6/P6,"") | S6: =IFERROR(O6/I6/P6,"") | T6: https://www.gasonet.in/files/Tender-%20Domestic%20Service%20Regulator.pdf | U6: Yes | V6: Qty mix: 800 domestic, 8 service, others? extract details
A7: T-0004 | B7: Vadodara Gas | C7: VGL Tenders | D7: P066/23-24 | E7: 2025-01-01 | F7: Awarded | G7: Domestic Regulator | H7: Domestic gas regulator | I7: 50000 | J7: nos | K7: Not found | L7: Unknown | P7: 106.75 | Q7: =IFERROR(O7/P7,"") | R7: =IFERROR(M7/I7/P7,"") | S7: =IFERROR(O7/I7/P7,"") | T7: https://www.vgl.co.in/wp-content/uploads/2025/pdf/Replies-to-Bidders-Domestic-Regulator-P066-23-24-Additional.pdf | U7: Yes | V7: Known quantity; price not found | Bot enrich; date=2026-07-01; type=pdf; score=230; Bot tespit/zenginlestirme (2026-07-01); meta:score=100;priority=High;source_type=html_link;closing_date=None;equipment=Domestic regulator;reasons=equipment:Domestic regulator,target regulator keyword,document source,quantity signal,tender reference signal; Bot clean extraction (2026-07-01); meta:score=100;priority=High;source_type=html_link;closing_date=None;equipment=Domestic gas regulator;quality_status=market_target;market_relevance=High;document_type=po_work_order;unit_price_inr=;amount_label=;matched_terms=Domestic gas regulator;reject_reasons=employment/corporate;scope=market_intelligence_only;excluded_scope=no_bid_or_offer_submission_automation
A201: T-0005 | B201: GAIL India | C201: GAIL India | F201: New Lead | H201: All Active Tenders | K201: Not found | L201: Unknown | T201: https://gailtenders.in/general_url.asp?val=4&inb=1 | U201: No | V201: Bot tarafindan tespit edildi (2026-07-01)
A202: T-0006 | B202: GAIL India | C202: GAIL India | F202: New Lead | H202: CORRIGENDUM | K202: Not found | L202: Unknown | T202: https://gailtenders.in/general_url.asp?val=4&inb=2 | U202: No | V202: Bot tarafindan tespit edildi (2026-07-01)
A203: T-0007 | B203: GAIL India | C203: GAIL India | F203: New Lead | H203: TENDER AWARDED | K203: Not found | L203: Unknown | T203: https://gailtenders.in/admin/AOC_param.asp | U203: No | V203: Bot tarafindan tespit edildi (2026-07-01)
A204: T-0008 | B204: GAIL India | C204: GAIL India | F204: New Lead | H204: https://gailtenders.in/tenderarchives_old.asp | K204: Not found | L204: Unknown | T204: https://gailtenders.in/tenderarchives_old.asp | U204: No | V204: Bot tarafindan tespit edildi (2026-07-01)
A205: T-0009 | B205: GAIL India | C205: GAIL India | D205: ERENCE | E205: 26-06-2026 | F205: New Lead | G205: Irrelevant / non-target | H205: E-Tenders | K205: Not found | L205: Unknown | T205: https://etenders.gov.in/eprocure/app | U205: No | V205: Bot tarafindan tespit edildi (2026-07-01); Bot tespit/zenginlestirme (2026-07-01); meta:score=40;priority=Medium;source_type=html_table;closing_date=21-12-2025;equipment=Irrelevant / non-target;reasons=irrelevant_equipment,station/skid keyword,quantity signal,commercial/price signal,tender reference signal,closing date signal; Bot clean extraction (2026-07-01); meta:score=55;priority=Medium;source_type=html_table;closing_date=21-12-2025;equipment=Regulating / metering station;quality_status=market_target;market_relevance=High;document_type=boq;unit_price_inr=;amount_label=;matched_terms=Regulating / metering station;reject_reasons=retail/cng station noise,civil/electrical only;scope=market_intelligence_only;excluded_scope=no_bid_or_offer_submission_automation
A206: T-0010 | B206: GAIL India | C206: GAIL India | F206: New Lead | H206: Click here to Login for uploadingTenders / Corrigendum | K206: Not found | L206: Unknown | T206: https://gailtenders.in/admin/index.asp | U206: No | V206: Bot tarafindan tespit edildi (2026-07-01)
A207: T-0011 | B207: GAIL India | C207: GAIL India | D207: TENDER WEBSITE | F207: Awarded | H207: Annual Procurement Plan | L207: Unknown | T207: https://gailtenders.in/pdf/APP2425002_19062024.pdf | U207: No | V207: Bot tarafindan tespit edildi (2026-07-01) | Bot enrich; date=2026-07-01; type=pdf; score=170; pdf_conf=Low
A208: T-0012 | B208: GAIL India | C208: GAIL India | F208: New Lead | H208: DETAILS OF PRE-TENDER CONFERENCE | K208: Not found | L208: Unknown | T208: https://gailtenders.in/new2.asp | U208: No | V208: Bot tarafindan tespit edildi (2026-07-01)
A209: T-0013 | B209: GAIL India | C209: GAIL India | D209: TENDER CONFERENCE | F209: New Lead | H209: ADDENDUM TO INSTRUCTIONS TO BIDDERS (INSTRUCTIONS FOR PARTICIPATION IN E-TENDER) | L209: Unknown | T209: https://gailtenders.in/AddendumtoITBeTender.pdf | U209: No | V209: Bot tarafindan tespit edildi (2026-07-01) | Bot enrich; date=2026-07-01; type=pdf; score=125; pdf_conf=Low
A210: T-0014 | B210: GAIL India | C210: GAIL India | F210: New Lead | G210: Unclassified | H210: A brief document about implementation of vendor invoice management system. | L210: Unknown | T210: https://gailebank.gail.co.in/gailtenders/annextures/Annexure1IntroductiontoVIMandSPARSHUpdated.pdf | U210: Yes | V210: Bot tarafindan tespit edildi (2026-07-01); Bot tespit/zenginlestirme (2026-07-01); meta:score=20;priority=Low;source_type=html_table;closing_date=;equipment=Unclassified;reasons=document source
A211: T-0015 | B211: GAIL India | C211: GAIL India | F211: New Lead | G211: Unclassified | H211: SPARSH Portal User Manual | L211: Unknown | T211: https://gailebank.gail.co.in/gailtenders/annextures/Annexure2SPARSHUsermanualUpdated.pdf | U211: Yes | V211: Bot tarafindan tespit edildi (2026-07-01); Bot tespit/zenginlestirme (2026-07-01); meta:score=20;priority=Low;source_type=html_table;closing_date=;equipment=Unclassified;reasons=document source
A212: T-0016 | B212: GAIL India | C212: GAIL India | F212: New Lead | G212: Unclassified | H212: SPARSH FAQs Document | L212: Unknown | T212: https://gailebank.gail.co.in/gailtenders/annextures/Annexure3SPARSHFAQDocReviewedUpdated.pdf | U212: Yes | V212: Bot tarafindan tespit edildi (2026-07-01); Bot tespit/zenginlestirme (2026-07-01); meta:score=20;priority=Low;source_type=html_table;closing_date=;equipment=Unclassified;reasons=document source
A213: T-0017 | B213: GAIL India | C213: GAIL India | F213: New Lead | G213: Unclassified | H213: Presentation containing information about various tab and buttons available of the portal. | L213: Unknown | T213: https://gailebank.gail.co.in/gailtenders/annextures/Annexure4PresentationonSPARSHUpdated.pdf | U213: Yes | V213: Bot tarafindan tespit edildi (2026-07-01); Bot tespit/zenginlestirme (2026-07-01); meta:score=20;priority=Low;source_type=html_table;closing_date=;equipment=Unclassified;reasons=document source
A214: T-0018 | B214: Indraprastha Gas (IGL) | C214: Indraprastha Gas (IGL) | F214: New Lead | H214: https://tenders.iglonline.net/dashboard | K214: Not found | L214: Unknown | T214: https://tenders.iglonline.net/dashboard | U214: No | V214: Bot tarafindan tespit edildi (2026-07-01)
A215: T-0019 | B215: Indraprastha Gas (IGL) | C215: Indraprastha Gas (IGL) | F215: New Lead | H215: Download Government Registration form | L215: Unknown | T215: https://www.iglonline.net/uploads/files/FOR_GOVERNMENT_ACCOMODATION-.pdf | U215: Yes | V215: Bot tarafindan tespit edildi (2026-07-01)
A216: T-0020 | B216: Indraprastha Gas (IGL) | C216: Indraprastha Gas (IGL) | F216: New Lead | H216: Download your EMI Schedule | K216: Not found | L216: Unknown | T216: https://webonline.igl.co.in:8077/sap/bc/ui5_ui5/sap/zumcui5/index.html?installmentPlan&_ga=2.5668855 | U216: No | V216: Bot tarafindan tespit edildi (2026-07-01)
A217: T-0021 | B217: Indraprastha Gas (IGL) | C217: Indraprastha Gas (IGL) | F217: New Lead | H217: Download NOC | K217: Not found | L217: Unknown | T217: https://webonline.igl.co.in:8077/sap/bc/ui5_ui5/sap/zumcui5/index.html?nocDownload&_ga=2.56688554.18 | U217: No | V217: Bot tarafindan tespit edildi (2026-07-01)
A218: T-0022 | B218: Indraprastha Gas (IGL) | C218: Indraprastha Gas (IGL) | F218: New Lead | H218: Upload Pan | K218: Not found | L218: Unknown | T218: https://tenders.iglonline.net/uploadPan | U218: No | V218: Bot tarafindan tespit edildi (2026-07-01)
A219: T-0023 | B219: Indraprastha Gas (IGL) | C219: Indraprastha Gas (IGL) | F219: New Lead | H219: https://tenders.iglonline.net//dashboard | K219: Not found | L219: Unknown | T219: https://tenders.iglonline.net//dashboard | U219: No | V219: Bot tarafindan tespit edildi (2026-07-01)
A220: T-0024 | B220: Indraprastha Gas (IGL) | C220: Indraprastha Gas (IGL) | F220: New Lead | H220: Active Tenders and Corrigendum/Addendum | K220: Not found | L220: Unknown | T220: https://tenders.iglonline.net/tenderList | U220: No | V220: Bot tarafindan tespit edildi (2026-07-01)
A221: T-0025 | B221: Indraprastha Gas (IGL) | C221: Indraprastha Gas (IGL) | F221: New Lead | H221: Old Tenders | K221: Not found | L221: Unknown | T221: https://tenders.iglonline.net/old-tenders | U221: No | V221: Bot tarafindan tespit edildi (2026-07-01)
A222: T-0026 | B222: Indraprastha Gas (IGL) | C222: Indraprastha Gas (IGL) | F222: New Lead | H222: Expression of Interest | K222: Not found | L222: Unknown | T222: https://tenders.iglonline.net/expression-of-interest | U222: No | V222: Bot tarafindan tespit edildi (2026-07-01)
A223: T-0027 | B223: Indraprastha Gas (IGL) | C223: Indraprastha Gas (IGL) | F223: New Lead | H223: Old EOI | K223: Not found | L223: Unknown | T223: https://iglonline.net/old-eoi | U223: No | V223: Bot tarafindan tespit edildi (2026-07-01)
A224: T-0028 | B224: Indraprastha Gas (IGL) | C224: Indraprastha Gas (IGL) | F224: New Lead | H224: Bank Guarantee Format | L224: Unknown | T224: https://www.iglonline.net/uploads/files/CPBG_Original_Format.pdf | U224: Yes | V224: Bot tarafindan tespit edildi (2026-07-01)
A225: T-0029 | B225: Indraprastha Gas (IGL) | C225: Indraprastha Gas (IGL) | D225: TENDER NO. FOR | F225: Docs Found | H225: Bid Bond Proforma/Proforma of Bid | K225: INDRAPRASTHA GAS | L225: Unknown | T225: https://www.iglonline.net/uploads/files/BID_BOND_PROFORMA.pdf | U225: Yes | V225: Bot tarafindan tespit edildi (2026-07-01)
A226: T-0030 | B226: Indraprastha Gas (IGL) | C226: Indraprastha Gas (IGL) | F226: New Lead | H226: IGL GST Details | K226: INDRAPRASTHA GAS LIMITED | L226: Unknown | T226: https://www.iglonline.net/uploads/files/IGL GST Certificate Details_v2.pdf | U226: Yes | V226: Bot tarafindan tespit edildi (2026-07-01)
A227: T-0031 | B227: Indraprastha Gas (IGL) | C227: Indraprastha Gas (IGL) | F227: New Lead | H227: Vendor Evaluation Policy | L227: Unknown | T227: https://iglonline.net/uploads/files/Vendor_Evaluation_Policy_v2_01.pdf | U227: Yes | V227: Bot tarafindan tespit edildi (2026-07-01)
A228: T-0032 | B228: Indraprastha Gas (IGL) | C228: Indraprastha Gas (IGL) | F228: New Lead | H228: IGL Holiday Listing Policy | L228: Unknown | T228: https://www.iglonline.net/uploads/files/IGL_Holiday_Listing_Policy.pdf | U228: Yes | V228: Bot tarafindan tespit edildi (2026-07-01)
A229: T-0033 | B229: Indraprastha Gas (IGL) | C229: Indraprastha Gas (IGL) | F229: New Lead | H229: E-tender Guide | L229: Unknown | T229: https://www.iglonline.net/uploads/files/E-tender_guide_for_bidders.pdf | U229: Yes | V229: Bot tarafindan tespit edildi (2026-07-01)
A230: T-0034 | B230: Indraprastha Gas (IGL) | C230: Indraprastha Gas (IGL) | F230: New Lead | H230: Vendor Registration For e-tender Portal`s | K230: Not found | L230: Unknown | T230: https://petroleum.euniwizarde.com/HomePage/loadSiteHomePage/Vy66Wa1zwHmM99LvXvGIkA | U230: No | V230: Bot tarafindan tespit edildi (2026-07-01)
A231: T-0035 | B231: Indraprastha Gas (IGL) | C231: Indraprastha Gas (IGL) | F231: New Lead | H231: BEC For pre tender | L231: Unknown | T231: https://www.iglonline.net/uploads/files/BEC For pre tender.pdf | U231: Yes | V231: Bot tarafindan tespit edildi (2026-07-01)
A232: T-0036 | B232: Indraprastha Gas (IGL) | C232: Indraprastha Gas (IGL) | F232: New Lead | H232: SOR | K232: Not found | L232: Unknown | T232: https://www.iglonline.net/uploads/files/SOR.xlsx | U232: No | V232: Bot tarafindan tespit edildi (2026-07-01)
A233: T-0037 | B233: Indraprastha Gas (IGL) | C233: Indraprastha Gas (IGL) | F233: New Lead | H233: Tech. Specs | K233: Oldham, Spectrex Detronics Honeywell Net | L233: Unknown | M233: 100 | T233: https://www.iglonline.net/uploads/files/Tech_Specs.pdf | U233: Yes | V233: Bot tarafindan tespit edildi (2026-07-01)
A234: T-0038 | B234: Indraprastha Gas (IGL) | C234: Indraprastha Gas (IGL) | D234: erence | E234: 28-02-2025 | F234: New Lead | G234: Domestic gas regulator | H234: Pre-bid meeting for Implementation of vendor invoice system in IGL | L234: Unknown | T234: https://www.iglonline.net/uploads/files/VIM_Draft_scope.pdf | U234: Yes | V234: Bot tarafindan tespit edildi (2026-07-01); Bot clean extraction (2026-07-01); meta:score=10;priority=Low;source_type=html_table;closing_date=;equipment=Domestic gas regulator;quality_status=market_target;market_relevance=High;document_type=corrigendum;unit_price_inr=;amount_label=;matched_terms=Domestic gas regulator,Service / pressure regulator,Regulating / metering station,Skid / gas train,Gas filter station / filter equipment,Safety / shut-off equipment;reject_reasons=employment/corporate,non-product service,retail/cng station noise,civil/electrical only;scope=market_intelligence_only;excluded_scope=no_bid_or_offer_submission_automation
A235: T-0039 | B235: Indraprastha Gas (IGL) | C235: Indraprastha Gas (IGL) | D235: erence | E235: 28-02-2025 | F235: New Lead | G235: Domestic gas regulator | H235: Pre-tender Meet for Supply of Master Mass Flow Meter (Prover System) Used for Calibration of Flowmeters Used in CNG Dispensers and at LCV points on Igl Website | L235: Unknown | T235: https://www.iglonline.net/uploads/files/Pre_tender_meet.pdf | U235: No | V235: Bot tarafindan tespit edildi (2026-07-01); Bot clean extraction (2026-07-01); meta:score=10;priority=Low;source_type=html_table;closing_date=;equipment=Domestic gas regulator;quality_status=market_target;market_relevance=High;document_type=corrigendum;unit_price_inr=;amount_label=;matched_terms=Domestic gas regulator,Service / pressure regulator,Regulating / metering station,Skid / gas train,Gas filter station / filter equipment,Safety / shut-off equipment;reject_reasons=employment/corporate,non-product service,retail/cng station noise,civil/electrical only;scope=market_intelligence_only;excluded_scope=no_bid_or_offer_submission_automation
A236: T-0040 | B236: Indraprastha Gas (IGL) | C236: Indraprastha Gas (IGL) | D236: erence | E236: 28-02-2025 | F236: New Lead | G236: Domestic gas regulator | H236: Pre-Tender Meet for Procurement of Manual and Hydraulic Squeezers for Control Room Operation and Maintenance Work | K236: shall furnish to the Purchaser, the Contract Performance Bank | L236: Unknown | T236: https://www.iglonline.net/uploads/files/Pre_Tender_Squeezers.pdf | U236: Yes | V236: Bot tarafindan tespit edildi (2026-07-01); Bot clean extraction (2026-07-01); meta:score=10;priority=Low;source_type=html_table;closing_date=;equipment=Domestic gas regulator;quality_status=market_target;market_relevance=High;document_type=corrigendum;unit_price_inr=;amount_label=;matched_terms=Domestic gas regulator,Service / pressure regulator,Regulating / metering station,Skid / gas train,Gas filter station / filter equipment,Safety / shut-off equipment;reject_reasons=employment/corporate,non-product service,retail/cng station noise,civil/electrical only;scope=market_intelligence_only;excluded_scope=no_bid_or_offer_submission_automation
A237: T-0041 | B237: Indraprastha Gas (IGL) | C237: Indraprastha Gas (IGL) | D237: erence | E237: 28-02-2025 | F237: New Lead | G237: Domestic gas regulator | H237: DESIGN, SUPPLY, INSTALLATION, COMMISSIONING AND 10 YEARS OF OPERATION & COMPREHENSIVE MAINTENANCE OF 350 SCMH ELECTRIC MOTOR DRIVEN COMPRESSOR PACKAGES | I237: 1.0 | K237: before dispatch. 4. In case any new GAs is added (in future), within above mentioned states, bidder | L237: Unknown | M237: 4 | R237: 10000 | S237: 10000 | T237: https://www.iglonline.net/uploads/files/Pre Tender Meet for 350 SCMH EMD packages.pdf | U237: Yes | V237: Bot tarafindan tespit edildi (2026-07-01); Bot clean extraction (2026-07-01); meta:score=10;priority=Low;source_type=html_table;closing_date=;equipment=Domestic gas regulator;quality_status=market_target;market_relevance=High;document_type=corrigendum;unit_price_inr=;amount_label=;matched_terms=Domestic gas regulator,Service / pressure regulator,Regulating / metering station,Skid / gas train,Gas filter station / filter equipment,Safety / shut-off equipment;reject_reasons=employment/corporate,non-product service,retail/cng station noise,civil/electrical only;scope=market_intelligence_only;excluded_scope=no_bid_or_offer_submission_automation
A238: T-0042 | B238: Indraprastha Gas (IGL) | C238: Indraprastha Gas (IGL) | F238: New Lead | H238: View Tender | K238: Not found | L238: Unknown | T238: https://tenders.iglonline.net/tenderDetail/545/Active Tenders And Corrigendum-Addendum | U238: No | V238: Bot tarafindan tespit edildi (2026-07-01)
A239: T-0043 | B239: Indraprastha Gas (IGL) | C239: Indraprastha Gas (IGL) | F239: New Lead | H239: View Tender | K239: Not found | L239: Unknown | T239: https://tenders.iglonline.net/tenderDetail/544/Active Tenders And Corrigendum-Addendum | U239: No | V239: Bot tarafindan tespit edildi (2026-07-01)
A240: T-0044 | B240: Indraprastha Gas (IGL) | C240: Indraprastha Gas (IGL) | F240: New Lead | H240: View Tender | K240: Not found | L240: Unknown | T240: https://tenders.iglonline.net/tenderDetail/543/Active Tenders And Corrigendum-Addendum | U240: No | V240: Bot tarafindan tespit edildi (2026-07-01)
A241: T-0045 | B241: Indraprastha Gas (IGL) | C241: Indraprastha Gas (IGL) | F241: New Lead | H241: View Tender | K241: Not found | L241: Unknown | T241: https://tenders.iglonline.net/tenderDetail/542/Active Tenders And Corrigendum-Addendum | U241: No | V241: Bot tarafindan tespit edildi (2026-07-01)
A242: T-0046 | B242: Indraprastha Gas (IGL) | C242: Indraprastha Gas (IGL) | D242: Tender Ref. No. | F242: Docs Found | G242: Gas-related / review | H242: Corrigendum_1_CP18908.pdf | L242: Unknown | T242: https://tenders.iglonline.net/uploads/tender/Corrigendum_1_CP18908.pdf | U242: Yes | V242: Bot tarafindan tespit edildi (2026-07-01); Bot tespit/zenginlestirme (2026-07-01); meta:score=35;priority=Low;source_type=html_table;closing_date=;equipment=Gas-related / review;reasons=equipment:Gas-related / review,document source
A243: T-0047 | B243: Indraprastha Gas (IGL) | C243: Indraprastha Gas (IGL) | F243: New Lead | H243: View Tender | K243: Not found | L243: Unknown | T243: https://tenders.iglonline.net/tenderDetail/541/Active Tenders And Corrigendum-Addendum | U243: No | V243: Bot tarafindan tespit edildi (2026-07-01)
A244: T-0048 | B244: Indraprastha Gas (IGL) | C244: Indraprastha Gas (IGL) | D244: Tender Ref. No. | F244: Awarded | G244: Metering skid | H244: Corrigendum_1_CP18866.pdf | L244: Unknown | M244: 13 | T244: https://tenders.iglonline.net/uploads/tender/Corrigendum_1_CP18866.pdf | U244: Yes | V244: Bot tarafindan tespit edildi (2026-07-01) | Bot enrich; date=2026-07-01; type=pdf; score=230; pdf_conf=Medium
A245: T-0049 | B245: Indraprastha Gas (IGL) | C245: Indraprastha Gas (IGL) | F245: New Lead | H245: View Tender | K245: Not found | L245: Unknown | T245: https://tenders.iglonline.net/tenderDetail/540/Active Tenders And Corrigendum-Addendum | U245: No | V245: Bot tarafindan tespit edildi (2026-07-01)
A246: T-0050 | B246: Indraprastha Gas (IGL) | C246: Indraprastha Gas (IGL) | F246: New Lead | H246: View Tender | K246: Not found | L246: Unknown | T246: https://tenders.iglonline.net/tenderDetail/539/Active Tenders And Corrigendum-Addendum | U246: No | V246: Bot tarafindan tespit edildi (2026-07-01)
A247: T-0051 | B247: Indraprastha Gas (IGL) | C247: Indraprastha Gas (IGL) | F247: New Lead | H247: View Tender | K247: Not found | L247: Unknown | T247: https://tenders.iglonline.net/tenderDetail/538/Active Tenders And Corrigendum-Addendum | U247: No | V247: Bot tarafindan tespit edildi (2026-07-01)
A248: T-0052 | B248: Indraprastha Gas (IGL) | C248: Indraprastha Gas (IGL) | F248: New Lead | H248: View Tender | K248: Not found | L248: Unknown | T248: https://tenders.iglonline.net/tenderDetail/537/Active Tenders And Corrigendum-Addendum | U248: No | V248: Bot tarafindan tespit edildi (2026-07-01)
A249: T-0053 | B249: Indraprastha Gas (IGL) | C249: Indraprastha Gas (IGL) | F249: New Lead | H249: RTPBQ_CM18730.pdf | L249: Unknown | T249: https://tenders.iglonline.net/uploads/tender/RTPBQ_CM18730.pdf | U249: Yes | V249: Bot tarafindan tespit edildi (2026-07-01)
A250: T-0054 | B250: Indraprastha Gas (IGL) | C250: Indraprastha Gas (IGL) | F250: New Lead | H250: View Tender | K250: Not found | L250: Unknown | T250: https://tenders.iglonline.net/tenderDetail/536/Active Tenders And Corrigendum-Addendum | U250: No | V250: Bot tarafindan tespit edildi (2026-07-01)
A251: T-0055 | B251: Indraprastha Gas (IGL) | C251: Indraprastha Gas (IGL) | D251: TENDER NO. IGL/ET2/CP/CM18852 | F251: Docs Found | H251: RTBQ_CM18852.pdf | L251: Unknown | T251: https://tenders.iglonline.net/uploads/tender/RTBQ_CM18852.pdf | U251: Yes | V251: Bot tarafindan tespit edildi (2026-07-01)
A252: T-0056 | B252: Indraprastha Gas (IGL) | C252: Indraprastha Gas (IGL) | F252: New Lead | H252: View Tender | K252: Not found | L252: Unknown | T252: https://tenders.iglonline.net/tenderDetail/535/Active Tenders And Corrigendum-Addendum | U252: No | V252: Bot tarafindan tespit edildi (2026-07-01)
A253: T-0057 | B253: Indraprastha Gas (IGL) | C253: Indraprastha Gas (IGL) | F253: New Lead | H253: View Tender | K253: Not found | L253: Unknown | T253: https://tenders.iglonline.net/tenderDetail/534/Active Tenders And Corrigendum-Addendum | U253: No | V253: Bot tarafindan tespit edildi (2026-07-01)
A254: T-0058 | B254: Indraprastha Gas (IGL) | C254: Indraprastha Gas (IGL) | D254: Tender No. | F254: Awarded | G254: Metering skid | H254: Corrigendum_1_CP18845.pdf | L254: Unknown | M254: 100 | T254: https://tenders.iglonline.net/uploads/tender/Corrigendum_1_CP18845.pdf | U254: Yes | V254: Bot tarafindan tespit edildi (2026-07-01) | Bot enrich; date=2026-07-01; type=pdf; score=230; pdf_conf=Medium; Bot tespit/zenginlestirme (2026-07-01); meta:score=35;priority=Low;source_type=html_table;closing_date=;equipment=Gas-related / review;reasons=equipment:Gas-related / review,document source
A255: T-0059 | B255: Indraprastha Gas (IGL) | C255: Indraprastha Gas (IGL) | D255: tender norms. | F255: Awarded | G255: Metering skid | H255: RTPBQ_CP18845.pdf | K255: Contract start date | L255: Unknown | T255: https://tenders.iglonline.net/uploads/tender/RTPBQ_CP18845.pdf | U255: Yes | V255: Bot tarafindan tespit edildi (2026-07-01) | Bot enrich; date=2026-07-01; type=pdf; score=230; pdf_conf=Medium; Bot tespit/zenginlestirme (2026-07-01); meta:score=35;priority=Low;source_type=html_table;closing_date=;equipment=Gas-related / review;reasons=equipment:Gas-related / review,document source
A256: T-0060 | B256: Indraprastha Gas (IGL) | C256: Indraprastha Gas (IGL) | F256: New Lead | H256: View Tender | K256: Not found | L256: Unknown | T256: https://tenders.iglonline.net/tenderDetail/533/Active Tenders And Corrigendum-Addendum | U256: No | V256: Bot tarafindan tespit edildi (2026-07-01)
A257: T-0061 | B257: Indraprastha Gas (IGL) | C257: Indraprastha Gas (IGL) | D257: Tender No. | F257: Awarded | G257: Metering skid | H257: Corrigendum_1_CP18838.pdf | L257: Unknown | M257: 100 | T257: https://tenders.iglonline.net/uploads/tender/Corrigendum_1_CP18838.pdf | U257: Yes | V257: Bot tarafindan tespit edildi (2026-07-01) | Bot enrich; date=2026-07-01; type=pdf; score=230; pdf_conf=Medium; Bot tespit/zenginlestirme (2026-07-01); meta:score=35;priority=Low;source_type=html_table;closing_date=;equipment=Gas-related / review;reasons=equipment:Gas-related / review,document source
A258: T-0062 | B258: Indraprastha Gas (IGL) | C258: Indraprastha Gas (IGL) | D258: DOCUMENT | F258: Awarded | G258: Commercial regulator | H258: RTPBQ_CP18838.pdf | L258: Unknown | M258: 200 | T258: https://tenders.iglonline.net/uploads/tender/RTPBQ_CP18838.pdf | U258: Yes | V258: Bot tarafindan tespit edildi (2026-07-01) | Bot enrich; date=2026-07-01; type=pdf; score=230; pdf_conf=Medium; Bot tespit/zenginlestirme (2026-07-01); meta:score=35;priority=Low;source_type=html_table;closing_date=;equipment=Gas-related / review;reasons=equipment:Gas-related / review,document source
A259: T-0063 | B259: Indraprastha Gas (IGL) | C259: Indraprastha Gas (IGL) | F259: New Lead | H259: View Tender | K259: Not found | L259: Unknown | T259: https://tenders.iglonline.net/tenderDetail/532/Active Tenders And Corrigendum-Addendum | U259: No | V259: Bot tarafindan tespit edildi (2026-07-01)
A260: T-0064 | B260: Indraprastha Gas (IGL) | C260: Indraprastha Gas (IGL) | F260: New Lead | H260: Corrigendum_1_CP18827.pdf | L260: Unknown | T260: https://tenders.iglonline.net/uploads/tender/Corrigendum_1_CP18827.pdf | U260: Yes | V260: Bot tarafindan tespit edildi (2026-07-01)
A261: T-0065 | B261: Indraprastha Gas (IGL) | C261: Indraprastha Gas (IGL) | F261: New Lead | H261: RTPBQ_CP18827.pdf | K261: ABC is an MSME-registered company and the authorized | L261: Unknown | T261: https://tenders.iglonline.net/uploads/tender/RTPBQ_CP18827.pdf | U261: Yes | V261: Bot tarafindan tespit edildi (2026-07-01)
A262: T-0066 | B262: Indraprastha Gas (IGL) | C262: Indraprastha Gas (IGL) | F262: New Lead | H262: View Tender | K262: Not found | L262: Unknown | T262: https://tenders.iglonline.net/tenderDetail/531/Active Tenders And Corrigendum-Addendum | U262: No | V262: Bot tarafindan tespit edildi (2026-07-01)
A263: T-0067 | B263: Indraprastha Gas (IGL) | C263: Indraprastha Gas (IGL) | D263: TENDER NO. IGL/ET2/CP/CC18846 | F263: Awarded | G263: Gas-related / review | H263: Corrigendum_I_CC18846.pdf | L263: Unknown | T263: https://tenders.iglonline.net/uploads/tender/Corrigendum_I_CC18846.pdf | U263: Yes | V263: Bot tarafindan tespit edildi (2026-07-01) | Bot enrich; date=2026-07-01; type=pdf; score=230; pdf_conf=Low; Bot tespit/zenginlestirme (2026-07-01); meta:score=35;priority=Low;source_type=html_table;closing_date=;equipment=Gas-related / review;reasons=equipment:Gas-related / review,document source
A264: T-0068 | B264: Indraprastha Gas (IGL) | C264: Indraprastha Gas (IGL) | D264: Tender No.IGL/ET2/CP/CC18846 | F264: Awarded | G264: PRS / DRS / FRS | H264: RTBQ_CC18846.pdf | L264: Unknown | M264: 14.75 | T264: https://tenders.iglonline.net/uploads/tender/RTBQ_CC18846.pdf | U264: Yes | V264: Bot tarafindan tespit edildi (2026-07-01) | Bot enrich; date=2026-07-01; type=pdf; score=230; pdf_conf=Medium; Bot tespit/zenginlestirme (2026-07-01); meta:score=35;priority=Low;source_type=html_table;closing_date=;equipment=Gas-related / review;reasons=equipment:Gas-related / review,document source
A265: T-0069 | B265: Indraprastha Gas (IGL) | C265: Indraprastha Gas (IGL) | D265: TENDER NO. IGL/ET2/CP/CC18846 | F265: Awarded | G265: Gas-related / review | H265: Corrigendum_II_CC18846.pdf | L265: Unknown | T265: https://tenders.iglonline.net/uploads/tender/Corrigendum_II_CC18846.pdf | U265: Yes | V265: Bot tarafindan tespit edildi (2026-07-01) | Bot enrich; date=2026-07-01; type=pdf; score=230; pdf_conf=Low; Bot tespit/zenginlestirme (2026-07-01); meta:score=35;priority=Low;source_type=html_table;closing_date=;equipment=Gas-related / review;reasons=equipment:Gas-related / review,document source
A266: T-0070 | B266: Indraprastha Gas (IGL) | C266: Indraprastha Gas (IGL) | F266: New Lead | H266: View Tender | K266: Not found | L266: Unknown | T266: https://tenders.iglonline.net/tenderDetail/530/Active Tenders And Corrigendum-Addendum | U266: No | V266: Bot tarafindan tespit edildi (2026-07-01)
A267: T-0071 | B267: Indraprastha Gas (IGL) | C267: Indraprastha Gas (IGL) | F267: New Lead | H267: View Tender | K267: Not found | L267: Unknown | T267: https://tenders.iglonline.net/tenderDetail/529/Active Tenders And Corrigendum-Addendum | U267: No | V267: Bot tarafindan tespit edildi (2026-07-01)
A268: T-0072 | B268: Indraprastha Gas (IGL) | C268: Indraprastha Gas (IGL) | F268: New Lead | H268: Reply_to_Pre_Bid_Queries_CM18777.pdf | K268: may subsequently arrange and furnish the required land docume | L268: Unknown | T268: https://tenders.iglonline.net/uploads/tender/Reply_to_Pre_Bid_Queries_CM18777.pdf | U268: Yes | V268: Bot tarafindan tespit edildi (2026-07-01)
A269: T-0073 | B269: Indraprastha Gas (IGL) | C269: Indraprastha Gas (IGL) | D269: TENDER NO. IGL/ET2/CP/CM18777 | F269: Docs Found | H269: Corrigendum_I_CM18777.pdf | L269: Unknown | T269: https://tenders.iglonline.net/uploads/tender/Corrigendum_I_CM18777.pdf | U269: Yes | V269: Bot tarafindan tespit edildi (2026-07-01)
A270: T-0074 | B270: Indraprastha Gas (IGL) | C270: Indraprastha Gas (IGL) | D270: TENDER NO. IGL/ET2/CP/CM18777 | F270: Docs Found | H270: Corrigendum_II_CM18777.pdf | L270: Unknown | T270: https://tenders.iglonline.net/uploads/tender/Corrigendum_II_CM18777.pdf | U270: Yes | V270: Bot tarafindan tespit edildi (2026-07-01)
A271: T-0075 | B271: Indraprastha Gas (IGL) | C271: Indraprastha Gas (IGL) | F271: New Lead | H271: View Tender | K271: Not found | L271: Unknown | T271: https://tenders.iglonline.net/tenderDetail/528/Active Tenders And Corrigendum-Addendum | U271: No | V271: Bot tarafindan tespit edildi (2026-07-01)
A272: T-0076 | B272: Indraprastha Gas (IGL) | C272: Indraprastha Gas (IGL) | D272: document | F272: Awarded | G272: FRS | H272: Corrigendum_1_CP18797.pdf | L272: Unknown | T272: https://tenders.iglonline.net/uploads/tender/Corrigendum_1_CP18797.pdf | U272: Yes | V272: Bot tarafindan tespit edildi (2026-07-01) | Bot enrich; date=2026-07-01; type=pdf; score=330; pdf_conf=Low
A273: T-0077 | B273: Indraprastha Gas (IGL) | C273: Indraprastha Gas (IGL) | D273: document | F273: Awarded | G273: FRS | H273: Corrigendum_2_CP18797.pdf | K273: Not found | L273: Unknown | T273: https://tenders.iglonline.net/uploads/tender/Corrigendum_2_CP18797.pdf | U273: No | V273: Bot tarafindan tespit edildi (2026-07-01) | Bot enrich; date=2026-07-01; type=pdf; score=330; pdf_conf=Low
A274: T-0078 | B274: Indraprastha Gas (IGL) | C274: Indraprastha Gas (IGL) | D274: Loading | F274: Awarded | G274: FRS | H274: RTPBQ_CP18797.pdf | K274: Not found | L274: Unknown | M274: 2000 | T274: https://tenders.iglonline.net/uploads/tender/RTPBQ_CP18797.pdf | U274: No | V274: Bot tarafindan tespit edildi (2026-07-01) | Bot enrich; date=2026-07-01; type=pdf; score=330; pdf_conf=Medium
A275: T-0079 | B275: Indraprastha Gas (IGL) | C275: Indraprastha Gas (IGL) | D275: DOCUMENT | F275: Awarded | G275: FRS | H275: RTPBQ_2_CP18797.pdf | K275: Not found | L275: Unknown | T275: https://tenders.iglonline.net/uploads/tender/RTPBQ_2_CP18797.pdf | U275: No | V275: Bot tarafindan tespit edildi (2026-07-01) | Bot enrich; date=2026-07-01; type=pdf; score=330; pdf_conf=Low
A276: T-0080 | B276: Indraprastha Gas (IGL) | C276: Indraprastha Gas (IGL) | F276: New Lead | H276: View Tender | K276: Not found | L276: Unknown | T276: https://tenders.iglonline.net/tenderDetail/527/Active Tenders And Corrigendum-Addendum | U276: No | V276: Bot tarafindan tespit edildi (2026-07-01)
A277: T-0081 | B277: Indraprastha Gas (IGL) | C277: Indraprastha Gas (IGL) | D277: DOCUMENT | F277: Awarded | G277: Gas-related / review | H277: Corrigendum_I_CC18800.pdf | K277: Not found | L277: Unknown | T277: https://tenders.iglonline.net/uploads/tender/Corrigendum_I_CC18800.pdf | U277: No | V277: Bot tarafindan tespit edildi (2026-07-01) | Bot enrich; date=2026-07-01; type=pdf; score=230; pdf_conf=Low; Bot tespit/zenginlestirme (2026-07-01); meta:score=35;priority=Low;source_type=html_table;closing_date=;equipment=Gas-related / review;reasons=equipment:Gas-related / review,document source
A278: T-0082 | B278: Indraprastha Gas (IGL) | C278: Indraprastha Gas (IGL) | D278: DOCUMENT | F278: Awarded | G278: Gas-related / review | H278: Corrigendum_II_CC18800.pdf | K278: Not found | L278: Unknown | T278: https://tenders.iglonline.net/uploads/tender/Corrigendum_II_CC18800.pdf | U278: No | V278: Bot tarafindan tespit edildi (2026-07-01) | Bot enrich; date=2026-07-01; type=pdf; score=230; pdf_conf=Low; Bot tespit/zenginlestirme (2026-07-01); meta:score=35;priority=Low;source_type=html_table;closing_date=;equipment=Gas-related / review;reasons=equipment:Gas-related / review,document source
A279: T-0083 | B279: Indraprastha Gas (IGL) | C279: Indraprastha Gas (IGL) | F279: New Lead | H279: View Tender | K279: Not found | L279: Unknown | T279: https://tenders.iglonline.net/tenderDetail/526/Active Tenders And Corrigendum-Addendum | U279: No | V279: Bot tarafindan tespit edildi (2026-07-01)
A280: T-0084 | B280: Indraprastha Gas (IGL) | C280: Indraprastha Gas (IGL) | F280: New Lead | H280: RTBQ_CM18824.pdf | K280: Not found | L280: Unknown | T280: https://tenders.iglonline.net/uploads/tender/RTBQ_CM18824.pdf | U280: No | V280: Bot tarafindan tespit edildi (2026-07-01)
A281: T-0085 | B281: Indraprastha Gas (IGL) | C281: Indraprastha Gas (IGL) | F281: New Lead | H281: CORRIGENDUM_I_CM18824.pdf | K281: Not found | L281: Unknown | T281: https://tenders.iglonline.net/uploads/tender/CORRIGENDUM_I_CM18824.pdf | U281: No | V281: Bot tarafindan tespit edildi (2026-07-01)
A282: T-0086 | B282: Indraprastha Gas (IGL) | C282: Indraprastha Gas (IGL) | F282: New Lead | H282: View Tender | K282: Not found | L282: Unknown | T282: https://tenders.iglonline.net/tenderDetail/525/Active Tenders And Corrigendum-Addendum | U282: No | V282: Bot tarafindan tespit edildi (2026-07-01)
A283: T-0087 | B283: Indraprastha Gas (IGL) | C283: Indraprastha Gas (IGL) | F283: New Lead | H283: View Tender | K283: Not found | L283: Unknown | T283: https://tenders.iglonline.net/tenderDetail/524/Active Tenders And Corrigendum-Addendum | U283: No | V283: Bot tarafindan tespit edildi (2026-07-01)
A284: T-0088 | B284: Indraprastha Gas (IGL) | C284: Indraprastha Gas (IGL) | D284: DOCUMENT | F284: Awarded | G284: Gas-related / review | H284: Corrigendum_I_CC18786.pdf | K284: Not found | L284: Unknown | T284: https://tenders.iglonline.net/uploads/tender/Corrigendum_I_CC18786.pdf | U284: No | V284: Bot tarafindan tespit edildi (2026-07-01) | Bot enrich; date=2026-07-01; type=pdf; score=230; pdf_conf=Low; Bot tespit/zenginlestirme (2026-07-01); meta:score=35;priority=Low;source_type=html_table;closing_date=;equipment=Gas-related / review;reasons=equipment:Gas-related / review,document source
A285: T-0089 | B285: Indraprastha Gas (IGL) | C285: Indraprastha Gas (IGL) | D285: QUERIES | F285: Awarded | G285: Gas-related / review | H285: RTBQ_CC18786.pdf | K285: Not found | L285: Unknown | M285: 2000000 | T285: https://tenders.iglonline.net/uploads/tender/RTBQ_CC18786.pdf | U285: No | V285: Bot tarafindan tespit edildi (2026-07-01) | Bot enrich; date=2026-07-01; type=pdf; score=230; pdf_conf=Low; Bot tespit/zenginlestirme (2026-07-01); meta:score=35;priority=Low;source_type=html_table;closing_date=;equipment=Gas-related / review;reasons=equipment:Gas-related / review,document source
A286: T-0090 | B286: Indraprastha Gas (IGL) | C286: Indraprastha Gas (IGL) | F286: New Lead | H286: View Tender | K286: Not found | L286: Unknown | T286: https://tenders.iglonline.net/tenderDetail/523/Active Tenders And Corrigendum-Addendum | U286: No | V286: Bot tarafindan tespit edildi (2026-07-01)
A287: T-0091 | B287: Indraprastha Gas (IGL) | C287: Indraprastha Gas (IGL) | F287: New Lead | H287: View Tender | K287: Not found | L287: Unknown | T287: https://tenders.iglonline.net/tenderDetail/522/Active Tenders And Corrigendum-Addendum | U287: No | V287: Bot tarafindan tespit edildi (2026-07-01)
A288: T-0092 | B288: Indraprastha Gas (IGL) | C288: Indraprastha Gas (IGL) | F288: New Lead | G288: Gas-related / review | H288: RTPBQ_CP18807.pdf | K288: Not found | L288: Unknown | T288: https://tenders.iglonline.net/uploads/tender/RTPBQ_CP18807.pdf | U288: No | V288: Bot tarafindan tespit edildi (2026-07-01); Bot tespit/zenginlestirme (2026-07-01); meta:score=35;priority=Low;source_type=html_table;closing_date=;equipment=Gas-related / review;reasons=equipment:Gas-related / review,document source
A289: T-0093 | B289: Indraprastha Gas (IGL) | C289: Indraprastha Gas (IGL) | F289: New Lead | G289: Safety / shut-off equipment | H289: View Tender | K289: Not found | L289: Unknown | T289: https://tenders.iglonline.net/tenderDetail/521/Active Tenders And Corrigendum-Addendum | U289: No | V289: Bot tarafindan tespit edildi (2026-07-01); Bot clean extraction (2026-07-01); meta:score=45;priority=Medium;source_type=html_table;closing_date=;equipment=Safety / shut-off equipment;quality_status=market_target;market_relevance=High;document_type=corrigendum;unit_price_inr=;amount_label=;matched_terms=Safety / shut-off equipment;reject_reasons=;scope=market_intelligence_only;excluded_scope=no_bid_or_offer_submission_automation
A290: T-0094 | B290: Indraprastha Gas (IGL) | C290: Indraprastha Gas (IGL) | D290: DOCUMENT | F290: Awarded | G290: slam shut | H290: Corrigendum_1_CP18752.pdf | K290: Not found | L290: Unknown | T290: https://tenders.iglonline.net/uploads/tender/Corrigendum_1_CP18752.pdf | U290: No | V290: Bot tarafindan tespit edildi (2026-07-01) | Bot enrich; date=2026-07-01; type=pdf; score=330; pdf_conf=Low; Bot tespit/zenginlestirme (2026-07-01); meta:score=35;priority=Low;source_type=html_table;closing_date=;equipment=Safety valve;reasons=equipment:Safety valve,document source; Bot clean extraction (2026-07-01); meta:score=45;priority=Medium;source_type=html_table;closing_date=None;equipment=Safety / shut-off equipment;quality_status=market_target;market_relevance=High;document_type=corrigendum;unit_price_inr=;amount_label=;matched_terms=Safety / shut-off equipment;reject_reasons=employment/corporate;scope=market_intelligence_only;excluded_scope=no_bid_or_offer_submission_automation
A291: T-0095 | B291: Indraprastha Gas (IGL) | C291: Indraprastha Gas (IGL) | D291: DOCUMENT | F291: Awarded | G291: slam shut | H291: RTPBQ_CP18752.pdf | K291: Not found | L291: Unknown | T291: https://tenders.iglonline.net/uploads/tender/RTPBQ_CP18752.pdf | U291: No | V291: Bot tarafindan tespit edildi (2026-07-01) | Bot enrich; date=2026-07-01; type=pdf; score=330; pdf_conf=Low; Bot tespit/zenginlestirme (2026-07-01); meta:score=35;priority=Low;source_type=html_table;closing_date=;equipment=Safety valve;reasons=equipment:Safety valve,document source; Bot clean extraction (2026-07-01); meta:score=45;priority=Medium;source_type=html_table;closing_date=None;equipment=Safety / shut-off equipment;quality_status=market_target;market_relevance=High;document_type=corrigendum;unit_price_inr=;amount_label=;matched_terms=Safety / shut-off equipment;reject_reasons=;scope=market_intelligence_only;excluded_scope=no_bid_or_offer_submission_automation
A292: T-0096 | B292: Indraprastha Gas (IGL) | C292: Indraprastha Gas (IGL) | D292: document | F292: Awarded | G292: slam shut | H292: Corrigendum_2_CP18752.pdf | K292: Not found | L292: Unknown | T292: https://tenders.iglonline.net/uploads/tender/Corrigendum_2_CP18752.pdf | U292: No | V292: Bot tarafindan tespit edildi (2026-07-01) | Bot enrich; date=2026-07-01; type=pdf; score=330; pdf_conf=Low; Bot tespit/zenginlestirme (2026-07-01); meta:score=35;priority=Low;source_type=html_table;closing_date=;equipment=Safety valve;reasons=equipment:Safety valve,document source; Bot clean extraction (2026-07-01); meta:score=45;priority=Medium;source_type=html_table;closing_date=None;equipment=Safety / shut-off equipment;quality_status=market_target;market_relevance=High;document_type=corrigendum;unit_price_inr=;amount_label=;matched_terms=Safety / shut-off equipment;reject_reasons=employment/corporate;scope=market_intelligence_only;excluded_scope=no_bid_or_offer_submission_automation
A293: T-0097 | B293: Indraprastha Gas (IGL) | C293: Indraprastha Gas (IGL) | D293: document | F293: Awarded | G293: slam shut | H293: Corrigendum_3_CP18752.pdf | K293: Not found | L293: Unknown | T293: https://tenders.iglonline.net/uploads/tender/Corrigendum_3_CP18752.pdf | U293: No | V293: Bot tarafindan tespit edildi (2026-07-01) | Bot enrich; date=2026-07-01; type=pdf; score=330; pdf_conf=Low; Bot tespit/zenginlestirme (2026-07-01); meta:score=35;priority=Low;source_type=html_table;closing_date=;equipment=Safety valve;reasons=equipment:Safety valve,document source; Bot clean extraction (2026-07-01); meta:score=45;priority=Medium;source_type=html_table;closing_date=None;equipment=Safety / shut-off equipment;quality_status=market_target;market_relevance=High;document_type=corrigendum;unit_price_inr=;amount_label=;matched_terms=Safety / shut-off equipment;reject_reasons=employment/corporate;scope=market_intelligence_only;excluded_scope=no_bid_or_offer_submission_automation
A294: T-0098 | B294: Indraprastha Gas (IGL) | C294: Indraprastha Gas (IGL) | D294: DOCUMENT | F294: Awarded | G294: slam shut | H294: RTPBQ_2_CP18752.pdf | K294: Indraprastha Gas Limited Consultant | L294: Unknown | T294: https://tenders.iglonline.net/uploads/tender/RTPBQ_2_CP18752.pdf | U294: No | V294: Bot tarafindan tespit edildi (2026-07-01) | Bot enrich; date=2026-07-01; type=pdf; score=330; pdf_conf=Medium; Bot tespit/zenginlestirme (2026-07-01); meta:score=35;priority=Low;source_type=html_table;closing_date=;equipment=Safety valve;reasons=equipment:Safety valve,document source; Bot clean extraction (2026-07-01); meta:score=45;priority=Medium;source_type=html_table;closing_date=None;equipment=Safety / shut-off equipment;quality_status=market_target;market_relevance=High;document_type=corrigendum;unit_price_inr=;amount_label=;matched_terms=Safety / shut-off equipment;reject_reasons=civil/electrical only;scope=market_intelligence_only;excluded_scope=no_bid_or_offer_submission_automation
...

Sheet 05 Technical Database
A1: 05 Technical Database
A3: Tender ID | B3: Product Segment | C3: Model/Type | D3: Inlet Pressure | E3: Outlet Pressure | F3: Capacity | G3: Accuracy Class | H3: Lock-up / SG | I3: OPSO | J3: UPSO | K3: Relief | L3: Monitor | M3: Body Material | N3: Connection | O3: Standard | P3: TPI / Certification | Q3: Source Page / URL | R3: Notes
A4: T-0003 | B4: Domestic Regulator | C4: To extract | D4: 100 mbar | E4: 21 mbar | F4: To extract | G4: To extract | H4: To extract | I4: To extract | J4: To extract | K4: To extract | L4: No/To extract | M4: To extract | N4: To extract | O4: To extract | P4: To extract | Q4: https://www.gasonet.in/files/Tender-%20Domestic%20Service%20Regulator.pdf | R4: Fill from datasheet
A5: T-0003 | B5: Service Regulator | C5: To extract | D5: To extract | E5: To extract | F5: 10/25/50/100 SCMH? | G5: To extract | H5: To extract | I5: To extract | J5: To extract | K5: To extract | L5: To extract | M5: To extract | N5: To extract | O5: To extract | P5: To extract | Q5: https://www.gasonet.in/files/Tender-%20Domestic%20Service%20Regulator.pdf | R5: Important ESKA segment

Sheet 06 Price Intelligence
A1: 06 Price Intelligence
A3: Tender ID | B3: Company | C3: Year | D3: Product Segment | E3: Capacity | F3: Qty | G3: Winner | H3: Brand | I3: Total INR Basic | J3: Total EUR Basic | K3: Unit EUR Basic | L3: Unit EUR Incl GST | M3: Confidence | N3: Source URL | O3: Notes
A4: T-0001 | B4: GAIL India | C4: 2025 | D4: Metering skid | E4: RPD metering skid | F4: 3 | G4: Kimpex Flow Pvt. Ltd. | H4: Unknown | I4: ='04 Tender Register'!M4 | J4: ='04 Tender Register'!Q4 | K4: ='04 Tender Register'!R4 | L4: ='04 Tender Register'!S4 | M4: Medium | N4: https://gailtenders.in/Gailtenders/writereaddata/AOC/loa_20250806_102439.pdf | O4: Not regulator; useful skid benchmark
A5: T-0003 | B5: Gasonet | C5: 2024 | D5: Domestic + Service Regulator | E5: Mixed | F5: 938 | G5: Not found | H5: Unknown | M5: Low | N5: https://www.gasonet.in/files/Tender-%20Domestic%20Service%20Regulator.pdf | O5: Await price bid/award
A6: T-0004 | B6: Vadodara Gas | C6: 2025 | D6: Domestic Regulator | E6: Domestic | F6: 50000 | G6: Not found | H6: Unknown | M6: Low | N6: https://www.vgl.co.in/wp-content/uploads/2025/pdf/Replies-to-Bidders-Domestic-Regulator-P066-23-24-Additional.pdf | O6: Await award price
A7: T-0037 | B7: Indraprastha Gas (IGL) | C7: 2026 | G7: Oldham, Spectrex Detronics Honeywell Net | H7: Unknown | I7: 100 | M7: Medium | N7: https://www.iglonline.net/uploads/files/Tech_Specs.pdf | O7: Bot tarafindan tespit edildi, dogrulama gerekli
A8: T-0041 | B8: Indraprastha Gas (IGL) | C8: 2026 | G8: Not found | H8: Unknown | I8: 4 | M8: Low | N8: https://www.iglonline.net/uploads/files/Pre Tender Meet for 350 SCMH EMD packages.pdf | O8: Bot tarafindan tespit edildi, dogrulama gerekli
A9: T-2514 | B9: Indraprastha Gas (IGL) | C9: 2026 | D9: Service / pressure regulator | G9: of reciprocating ELECTRIC MOTOR Driven compressor packages of 1200 SCMH or higher capacity handling h | H9: Unknown | I9: 114122000 | M9: Medium | N9: https://www.iglonline.net/uploads/files/Tender Document for Pre Tender Meet_1200 EMD.pdf | O9: Bot clean extraction (2026-08-15); meta:score=10;priority=Low;source_type=html_table;closing_date=None;equipment=Service / pressure regulator;quality_status=market_target;market_relevance=High;document_type=award;unit_price_inr=;amount_label=currency_near_total;matched_terms=Service / pressure regulator,Regulating / metering station,Skid / gas train,Gas filter station / filter equipment,Safety / shut-off equipment;reject_reasons=employment/corporate,non-product service,retail/cng station noise,civil/electrical only;scope=market_intelligence_only;excluded_scope=no_bid_or_offer_submission_automation
A10: T-2515 | B10: Indraprastha Gas (IGL) | C10: 2026 | D10: Service / pressure regulator | G10: of reciprocating Gas Engine Driven compressor packages of 1200 SCMH or higher capacity handling hydro | H10: Unknown | I10: 133671000 | M10: Medium | N10: https://www.iglonline.net/uploads/files/Tender Document for PTM_1200 GED.pdf | O10: Bot clean extraction (2026-08-15); meta:score=10;priority=Low;source_type=html_table;closing_date=None;equipment=Service / pressure regulator;quality_status=market_target;market_relevance=High;document_type=award;unit_price_inr=;amount_label=currency_near_total;matched_terms=Service / pressure regulator,Regulating / metering station,Skid / gas train,Gas filter station / filter equipment,Safety / shut-off equipment;reject_reasons=employment/corporate,non-product service,retail/cng station noise;scope=market_intelligence_only;excluded_scope=no_bid_or_offer_submission_automation
A11: T-2516 | B11: Indian Oil Corporation (IOCL CGD) | C11: 2026 | D11: Regulating / metering station | F11: 33000 | G11: Not found | H11: Unknown | I11: 2000 | K11: 0.060606061 | L11: 0.060606061 | M11: Medium | N11: https://iocl.com/Contents/Upload/Future_Procurement_Plan25-26.pdf | O11: Bot clean extraction (2026-08-15); meta:score=100;priority=Low;source_type=html_link;closing_date=None;equipment=Regulating / metering station;quality_status=market_target;market_relevance=High;document_type=unknown;unit_price_inr=0.06060606060606061;amount_label=currency_near_total;matched_terms=Regulating / metering station,Skid / gas train,Gas filter station / filter equipment,Safety / shut-off equipment;reject_reasons=retail/cng station noise,civil/electrical only;scope=market_intelligence_only;excluded_scope=no_bid_or_offer_submission_automation
A12: T-2517 | B12: Indian Oil Corporation (IOCL CGD) | C12: 2026 | D12: Regulating / metering station | G12: etc.). However, existing Service Provider / Job Contractor / Labour Contractor will be eligible to ap | H12: Unknown | I12: 1500000 | M12: Medium | N12: https://iocl.com/uploads/Industry_COCO _SP_Selection_Brochure_05032026.pdf | O12: Bot clean extraction (2026-08-15); meta:score=60;priority=Low;source_type=html_link;closing_date=None;equipment=Regulating / metering station;quality_status=market_target;market_relevance=High;document_type=award;unit_price_inr=;amount_label=currency_near_total;matched_terms=Regulating / metering station;reject_reasons=employment/corporate,non-product service;scope=market_intelligence_only;excluded_scope=no_bid_or_offer_submission_automation
A13: T-2536 | B13: Maharashtra Natural Gas (MNGL) | C13: 2026 | D13: Regulating / metering station | G13: shall be measured through an authorized competent person and the payment shall be made by MNGL | H13: Unknown | M13: Medium | N13: https://mngl.in/storage/193889/120_Tender-Document-for-CGS-in-Hadapsar-area-of-Pune-GA.pdf | O13: Bot clean extraction (2026-10-05); meta:score=90;priority=High;source_type=html_table;closing_date=None;equipment=Regulating / metering station;quality_status=market_target;market_relevance=High;document_type=award;unit_price_inr=;amount_label=;matched_terms=Regulating / metering station;reject_reasons=employment/corporate;scope=market_intelligence_only;excluded_scope=no_bid_or_offer_submission_automation

Sheet 07 Competitor DB
A1: 07 Competitor DB
A3: Competitor | B3: Country | C3: Role | D3: Likely Segment | E3: Website | F3: Relevance | G3: Notes
A4: Vanaz Engineers | B4: India | C4: OEM | D4: Domestic/service/industrial regulators | E4: https://vanaz.com | F4: High | G4: Frequently seen in Indian gas market
A5: Pietro Fiorentini | B5: Italy/India | C5: OEM | D5: Industrial/service regulators, stations | E5: https://www.fiorentini.com | F5: High | G5: Strong C&I/PRS/MRS competitor
A6: Honeywell / Elster | B6: USA/India | C6: OEM | D6: Meters/regulators | E6: https://process.honeywell.com | F6: Medium | G6: Often in meter/regulator ecosystem
A7: Itron | B7: USA/India | C7: OEM | D7: Meters/regulators | E7: https://www.itron.com | F7: Medium | G7: Domestic/commercial gas ecosystem
A8: Mesura Nirmal Gas Controls | B8: India | C8: OEM | D8: Domestic/service regulators | E8: https://mesura.in | F8: High | G8: Indian regulator competitor
A9: Kabsons Gas Equipment | B9: India | C9: OEM | D9: Domestic regulators | E9: https://kabsons.com | F9: High | G9: Awarded domestic regulator source found
A10: Prabha Electronics | B10: India | C10: Supplier/OEM | D10: Domestic regulators/meters | E10: To verify | F10: Medium | G10: Award source found in tender portals
A11: Madas | B11: Italy | C11: OEM | D11: Gas regulators/filters/SSV | E11: https://www.madas.it | F11: Medium | G11: Possible imported competitor
A12: Emerson / Fisher | B12: USA/India | C12: OEM | D12: Industrial regulators | E12: https://www.emerson.com | F12: Medium | G12: Industrial/PRS segment
A13: Kromschroeder / Honeywell | B13: Germany/USA | C13: OEM | D13: Gas controls | E13: https://process.honeywell.com | F13: Medium | G13: Gas train components
A14: ESKA Valve | B14: Türkiye | C14: OEM | D14: Domestic/service/industrial regulators | E14: https://eskavalve.com | F14: Target | G14: Our benchmark row

Sheet 08 Source Log
A1: 08 Source Log
A3: Source | B3: Use | C3: URL
A4: PNGRB CGD authorisation list | B4: Official regulator list for GA/entity mapping | C4: https://pngrb.gov.in/eng-web/cgd-auth.html
A5: PNGRB State and Entity-wise PDF | B5: Entity-wise list of GAs | C5: https://pngrb.gov.in/pdf/faqs/List_entities_with_States%26GA%27s.pdf
A6: Gujarat Gas Tenders | B6: Official tender page; nProcure instructions | C6: https://www.gujaratgas.com/tenders/
A7: Torrent Gas Vendor Registration | B7: Vendor page and procurement email | C7: https://www.torrentgas.com/User/Info/Vendor
A8: GAIL Gas Vendor Zone | B8: Tender information/vendor zone | C8: https://gailgas.com/stakeholder-zone/vendor-zone
A9: IGL Tender Portal | B9: Active tenders and vendor portal | C9: https://tenders.iglonline.net/tenderList
A10: MNGL Active Tenders | B10: Active tenders page | C10: https://mngl.in/active-tenders
A11: MNGL Instructions | B11: CPPP/DSC online bid instructions | C11: https://mngl.in/vendor/instructions-to-bridders
A12: Gasonet Tenders | B12: Gasonet official tender page | C12: https://www.gasonet.in/tenders.html
A13: Gasonet Regulator PDF | B13: Domestic and service regulator tender PDF | C13: https://www.gasonet.in/files/Tender-%20Domestic%20Service%20Regulator.pdf
A14: CPPP/eProcure | B14: Central eProcurement portal | C14: https://www.etenders.gov.in/eprocure/app
... A144: 2026-10-25 09:43 | B144: Clean tarama: 0 yeni ihale, 0 yeni fiyat kaydi, 0 zenginlestirme, 105 non-target atlandi | C144: bot

Sheet 00 Dashboard
A1: India Procurement Intelligence Database
A3: Created for | B3: ESKA India regulator price/tender intelligence | D3: Tier | E3: Count
A4: Created on | B4: 2026-02-04 | D4: Tier 1 | E4: =COUNTIF('01 Portal Master'!A4:A200,"Tier 1")
A5: Portal rows | B5: =COUNTA('01 Portal Master'!B4:B200) | D5: Tier 2 | E5: =COUNTIF('01 Portal Master'!A4:A200,"Tier 2")
A6: High relevance targets | B6: =COUNTIF('01 Portal Master'!H4:H200,"High") | D6: Tier 3 | E6: =COUNTIF('01 Portal Master'!A4:A200,"Tier 3")
A7: Tenders logged | B7: =COUNTA('04 Tender Register'!A4:A500)
A8: Awarded / price rows | B8: =COUNTIF('04 Tender Register'!F4:F500,"Awarded")
A9: Primary search portal | B9: CPPP / GAIL / IGL / GGL / MNGL / Gasonet
A10: FX default INR/EUR | B10: 106.75
A11: Next weekly action | B11: Add 10 PDFs and extract quantities/prices
